{
  "version": 3,
  "middleware": {
    "/": {
      "files": [
        "server/edge-runtime-webpack.js",
        "server/src/middleware.js"
      ],
      "name": "src/middleware",
      "page": "/",
      "matchers": [
        {
          "regexp": "^(?:\\/(_next\\/data\\/[^/]{1,}))?\\/eventDetails(?:\\/((?:[^\\/#\\?]+?)(?:\\/(?:[^\\/#\\?]+?))*))?(\\.json)?[\\/#\\?]?$",
          "originalSource": "/eventDetails/:path*"
        },
        {
          "regexp": "^(?:\\/(_next\\/data\\/[^/]{1,}))?\\/dashboard(?:\\/((?:[^\\/#\\?]+?)(?:\\/(?:[^\\/#\\?]+?))*))?(\\.json)?[\\/#\\?]?$",
          "originalSource": "/dashboard/:path*"
        },
        {
          "regexp": "^(?:\\/(_next\\/data\\/[^/]{1,}))?\\/profile(?:\\/((?:[^\\/#\\?]+?)(?:\\/(?:[^\\/#\\?]+?))*))?(\\.json)?[\\/#\\?]?$",
          "originalSource": "/profile/:path*"
        },
        {
          "regexp": "^(?:\\/(_next\\/data\\/[^/]{1,}))?(?:\\/(\\/?index|\\/?index\\.json))?[\\/#\\?]?$",
          "originalSource": "/"
        },
        {
          "regexp": "^(?:\\/(_next\\/data\\/[^/]{1,}))?\\/signup(\\.json)?[\\/#\\?]?$",
          "originalSource": "/signup"
        }
      ],
      "wasm": [],
      "assets": [],
      "env": {
        "__NEXT_BUILD_ID": "LP-uX1aul5pqZCLJHvkY_",
        "NEXT_SERVER_ACTIONS_ENCRYPTION_KEY": "zfddyRbnvBF/hdmKoUD/a4xPt6xe0GyUhwqp4W9hubI=",
        "__NEXT_PREVIEW_MODE_ID": "3090edcce5d9c87e303bb1023ba75195",
        "__NEXT_PREVIEW_MODE_ENCRYPTION_KEY": "add2018d0c13b95ec5a1ab5e5cedc5e5a49efc4bfd93483fb08cc33ffe536e8e",
        "__NEXT_PREVIEW_MODE_SIGNING_KEY": "7b2689767baa7e037680178d5a04867067264f4543aa45433a521e2c8f3dd1f1"
      }
    }
  },
  "functions": {},
  "sortedMiddleware": [
    "/"
  ]
}